jos/__init__.py
jos/client.py
jos/utils.py
jos-0.1.2.dist-info/RECORD
jos-0.1.2.dist-info/METADATA
jos-0.1.2.dist-info/pydist.json
jos-0.1.2.dist-info/top_level.txt
jos-0.1.2.dist-info/DESCRIPTION.rst
jos-0.1.2.dist-info/WHEEL
