Metadata-Version: 2.0
Name: jos
Version: 0.1.2
Summary: Jingdong API Client
Home-page: https://github.com/verycb/jos
Author: VeryCB
Author-email: imcaibin@gmail.com
License: MIT
Keywords: jingdong,jos
Platform: UNKNOWN
Classifier: Development Status :: 3 - Alpha
Classifier: Environment :: Web Environment
Classifier: Intended Audience :: Developers
Classifier: License :: OSI Approved :: MIT License
Classifier: Operating System :: OS Independent
Classifier: Programming Language :: Python
Classifier: Programming Language :: Python :: 2.7
Classifier: Topic :: Software Development :: Libraries :: Python Modules
Requires-Dist: requests (>=1.0)
